{"title":"Why Overpopulation Isn’t India’s Main Problem","markdown":{"yaml":{"title":"Why Overpopulation Isn’t India’s Main Problem","subtitle":"How majority of land is underutilized and large scale employment is missing","author":"Rick Rejeleene","date":"2025-10-25","date-format":"MMMM D, YYYY","categories":["India","Economy","Tamil Nadu","Geography","Land"],"description":"The Real Challenge is in Land Use and generating large scale employment","toc":true,"toc-title":"Table of Contents","toc-location":"left","number-sections":true,"number-depth":2},"headingText":"Most Common Myth of Overpopulation","containsRefs":false,"markdown":"\n\n\n![](../../images/population/population3.svg){width=\"69%\" height=\"70%\"}\n\nGrowing up in Tamil Nadu, I often heard from many people, the reason for India’s lack of economic development was,\n*“We have over a billion people, so that is our problem.” If we have smaller amount of population, our country would be wealthier”*\n\nThis belief is widespread among Indians, including many Tamils. \n\nHowever, to me this doesn’t seem to be the major issue. \nIn my view, Large population is a net-positive, advantageous for a country. \nEspecially in terms of economy, you have a larger market, it’s a blessing for Indians. \n\n### So, one might ask, How so? \n\nIndia has a large population. There is limited job opportunities for large population. \nSo, We need to find a large scalable solution, to create, provide and match working age population with a reasonable amount of jobs. \nThis would increase their purchasing power, productivity and consumption. Therefore, large population is a great strength.\n\n## Structure of India’s workforce\n\nAt present, India’s population in 2025 is about 1.46 billion people. \nThe median age is 28.8 years and roughly 607 million active workers in its labor force. \nMany prominent Indian Economists have raised about reliability[^arunkumar2] of the economic data of India [^arunkumar]. \nI am skeptical as well, you usually might have to decrease 2x or 3x times what the Indian Government[^internet] communicates to the broader public[^Rajeswari]. \n\nThe official statistics [^india] says, \nServices (≈55%), including IT, finance, and professional sectors\nIndustry (≈27%), including manufacturing and construction\nAgriculture (≈18%)\n\n\nAccording to Indian Economist, Professor Arun Kumar[^arunkumar3], India’s unorganized sector is about 94% of the workforce, only 6% are organized workforce. \n\n[^arunkumar]: [Why India’s GDP Estimates Miss The Mark – Arun Kumar](https://www.impriindia.com/insights/why-indias-gdp-estimates-miss-the-mark/#google_vignette)  \n[^arunkumar2]:[Why India might not have become fourth largest democracy](https://thewire.in/economy/has-india-really-become-the-fourth-largest-economy-five-reasons-to-ask)\n[^arunkumar3]: [Arun Kumar on India’s workforce – YouTube](https://www.youtube.com/watch?v=HVMfbpZyWsM)\n[^india]: [Provisional GDP Estimates 2025 – MoSPI](https://www.mospi.gov.in/sites/default/files/press_release/GDP_PR_Q1_2025-26_29082025.pdf)  \n[^Rajeswari]: [The unending saga of India’s GDP data – Business Standard](https://www.business-standard.com/opinion/columns/the-unending-saga-of-india-s-gdp-data-true-numbers-beyond-the-story-125091501596_1.html) \n[^internet]: [GDP Data Criticism - Reddit India](https://www.reddit.com/r/india/comments/1n3u92v/celebrating_78_gdp_growth_heres_what_the_data/)\n\n**Organized Sector and Unorganized Sector:**\n\nProfessor Arun Kumar and other economists estimate that about 94 percent of India’s workforce functions within the unorganized sector, \nwhile only 6 percent work in the formal or organized economy. \n\nOut of India’s roughly 607 million workers in 2025, that means only about 36 million people hold formal jobs, while nearly 571 million are in informal employment such as street vending, agriculture, domestic work, construction, gig services, or micro‑enterprise.\n\nSo, Formal employment: ≈ 36 million (6 %)\nInformal/unorganized employment: ≈ 571 million (94 %)\nContribution to GDP: the unorganized sector produces about 50 percent of India’s $4.1 trillion[^arunkumar4] GDP and as much as 60 percent of real daily output when under‑counted activities are included, so unorganized economy operates largely in cash, low‑productivity segments, and micro‑enterprise. It supports consumption at the base of the pyramid but lacks access to credit, technology, and institutional scale, which restrains productivity growth. Professor Arun Kumar argues that because most workers earn below ₹11000 per month, aggregate demand expands slowly and the formal sector cannot absorb labor fast enough.\n\n[^arunkumar4]: [Indian govt not prioritizing employment-generating sectors - Arun Kumar, CNBC 2025](https://www.cnbc.com/video/2025/07/23/indian-govt-not-prioritizing-employment-generating-sectors-economist.html)  \n\n### Hypothetical transformation: \n\n\nSo, Assume this transformation takes place, and half of the population, (≈ 730 million) instead worked in high‑productivity, high‑income organized‑sector jobs, annual GDP could reach $25 – 30 trillion (PPP) within a generation, roughly matching the output levels of the United States or European Union. This jump arises from multiplying labor‑productivity, severalfold and increasing effective capital per worker, causing large spillovers in demand, taxation, and innovation.\n\n**So,for example sake, you see, a large population is a boom, not a burden, to a nation.**\n**Therefore, population is an asset to India**\n\n## Underutilized, Undeveloped land for Population distribution\n\nAnother common objection about India’s population. \nWe in India have a large population. \nWe do not need more population growth, correct? \n\n![](../../images/population/population1.png){width=\"69%\" height=\"30%\"}\n\nI’d say, We have an issue of population distribution across large unused land, rather than population growth. \n\nCertainly, India has large population. It is overcrowded in urban areas. \nAcross India, We have large stretches of unused land.\nThese unused lands are not made productive in anyway, either for population or agriculture. \n\nTo give you an example, about 100-300 years ago, majority of the land was not used in America, it was built, made productive from scratch, So I ask Why not India? \n\n![](../../images/population/population2.png){width=\"69%\" height=\"30%\"}\n\nThe reason for underutilization of undeveloped lands in India, basic public services like education, healthcare, retail stores are clustered in major urban spaces, it is hard for average Indians to live far away from the medium, and large cities. \n\nIt is still possible for large segments of the population to be relocated. It requires support from the Indian Government.\nThey'd have to provide basic infrastructure support. In such a case, the stress, demand on urban Indian cities can be reduced vastly. \nThis can also improve quality of life for all India. \nThe solution lies in expanding employment and redistributing the population toward underutilized land across the country","srcMarkdownNoYaml":"\n\n## Most Common Myth of Overpopulation\n\n![](../../images/population/population3.svg){width=\"69%\" height=\"70%\"}\n\nGrowing up in Tamil Nadu, I often heard from many people, the reason for India’s lack of economic development was,\n*“We have over a billion people, so that is our problem.” If we have smaller amount of population, our country would be wealthier”*\n\nThis belief is widespread among Indians, including many Tamils. \n\nHowever, to me this doesn’t seem to be the major issue. \nIn my view, Large population is a net-positive, advantageous for a country. \nEspecially in terms of economy, you have a larger market, it’s a blessing for Indians. \n\n### So, one might ask, How so? \n\nIndia has a large population. There is limited job opportunities for large population. \nSo, We need to find a large scalable solution, to create, provide and match working age population with a reasonable amount of jobs. \nThis would increase their purchasing power, productivity and consumption. Therefore, large population is a great strength.\n\n## Structure of India’s workforce\n\nAt present, India’s population in 2025 is about 1.46 billion people. \nThe median age is 28.8 years and roughly 607 million active workers in its labor force. \nMany prominent Indian Economists have raised about reliability[^arunkumar2] of the economic data of India [^arunkumar]. \nI am skeptical as well, you usually might have to decrease 2x or 3x times what the Indian Government[^internet] communicates to the broader public[^Rajeswari]. \n\nThe official statistics [^india] says, \nServices (≈55%), including IT, finance, and professional sectors\nIndustry (≈27%), including manufacturing and construction\nAgriculture (≈18%)\n\n\nAccording to Indian Economist, Professor Arun Kumar[^arunkumar3], India’s unorganized sector is about 94% of the workforce, only 6% are organized workforce. \n\n[^arunkumar]: [Why India’s GDP Estimates Miss The Mark – Arun Kumar](https://www.impriindia.com/insights/why-indias-gdp-estimates-miss-the-mark/#google_vignette)  \n[^arunkumar2]:[Why India might not have become fourth largest democracy](https://thewire.in/economy/has-india-really-become-the-fourth-largest-economy-five-reasons-to-ask)\n[^arunkumar3]: [Arun Kumar on India’s workforce – YouTube](https://www.youtube.com/watch?v=HVMfbpZyWsM)\n[^india]: [Provisional GDP Estimates 2025 – MoSPI](https://www.mospi.gov.in/sites/default/files/press_release/GDP_PR_Q1_2025-26_29082025.pdf)  \n[^Rajeswari]: [The unending saga of India’s GDP data – Business Standard](https://www.business-standard.com/opinion/columns/the-unending-saga-of-india-s-gdp-data-true-numbers-beyond-the-story-125091501596_1.html) \n[^internet]: [GDP Data Criticism - Reddit India](https://www.reddit.com/r/india/comments/1n3u92v/celebrating_78_gdp_growth_heres_what_the_data/)\n\n**Organized Sector and Unorganized Sector:**\n\nProfessor Arun Kumar and other economists estimate that about 94 percent of India’s workforce functions within the unorganized sector, \nwhile only 6 percent work in the formal or organized economy. \n\nOut of India’s roughly 607 million workers in 2025, that means only about 36 million people hold formal jobs, while nearly 571 million are in informal employment such as street vending, agriculture, domestic work, construction, gig services, or micro‑enterprise.\n\nSo, Formal employment: ≈ 36 million (6 %)\nInformal/unorganized employment: ≈ 571 million (94 %)\nContribution to GDP: the unorganized sector produces about 50 percent of India’s $4.1 trillion[^arunkumar4] GDP and as much as 60 percent of real daily output when under‑counted activities are included, so unorganized economy operates largely in cash, low‑productivity segments, and micro‑enterprise. It supports consumption at the base of the pyramid but lacks access to credit, technology, and institutional scale, which restrains productivity growth. Professor Arun Kumar argues that because most workers earn below ₹11000 per month, aggregate demand expands slowly and the formal sector cannot absorb labor fast enough.\n\n[^arunkumar4]: [Indian govt not prioritizing employment-generating sectors - Arun Kumar, CNBC 2025](https://www.cnbc.com/video/2025/07/23/indian-govt-not-prioritizing-employment-generating-sectors-economist.html)  \n\n### Hypothetical transformation: \n\n\nSo, Assume this transformation takes place, and half of the population, (≈ 730 million) instead worked in high‑productivity, high‑income organized‑sector jobs, annual GDP could reach $25 – 30 trillion (PPP) within a generation, roughly matching the output levels of the United States or European Union. This jump arises from multiplying labor‑productivity, severalfold and increasing effective capital per worker, causing large spillovers in demand, taxation, and innovation.\n\n**So,for example sake, you see, a large population is a boom, not a burden, to a nation.**\n**Therefore, population is an asset to India**\n\n## Underutilized, Undeveloped land for Population distribution\n\nAnother common objection about India’s population. \nWe in India have a large population. \nWe do not need more population growth, correct? \n\n![](../../images/population/population1.png){width=\"69%\" height=\"30%\"}\n\nI’d say, We have an issue of population distribution across large unused land, rather than population growth. \n\nCertainly, India has large population. It is overcrowded in urban areas. \nAcross India, We have large stretches of unused land.\nThese unused lands are not made productive in anyway, either for population or agriculture. \n\nTo give you an example, about 100-300 years ago, majority of the land was not used in America, it was built, made productive from scratch, So I ask Why not India? \n\n![](../../images/population/population2.png){width=\"69%\" height=\"30%\"}\n\nThe reason for underutilization of undeveloped lands in India, basic public services like education, healthcare, retail stores are clustered in major urban spaces, it is hard for average Indians to live far away from the medium, and large cities. \n\nIt is still possible for large segments of the population to be relocated. It requires support from the Indian Government.\nThey'd have to provide basic infrastructure support. In such a case, the stress, demand on urban Indian cities can be reduced vastly. \nThis can also improve quality of life for all India. \nThe solution lies in expanding employment and redistributing the population toward underutilized land across the country"},"formats":{"html":{"identifier":{"display-name":"HTML","target-format":"html","base-format":"html"},"execute":{"fig-width":7,"fig-height":5,"fig-format":"retina","fig-dpi":96,"df-print":"default","error":false,"eval":true,"cache":null,"freeze":true,"echo":true,"output":true,"warning":true,"include":true,"keep-md":false,"keep-ipynb":false,"ipynb":null,"enabled":null,"daemon":null,"daemon-restart":false,"debug":false,"ipynb-filters":[],"ipynb-shell-interactivity":null,"plotly-connected":true,"engine":"markdown"},"render":{"keep-tex":false,"keep-typ":false,"keep-source":false,"keep-hidden":false,"prefer-html":false,"output-divs":true,"output-ext":"html","fig-align":"default","fig-pos":null,"fig-env":null,"code-fold":"none","code-overflow":"scroll","code-link":false,"code-line-numbers":false,"code-tools":false,"tbl-colwidths":"auto","merge-includes":true,"inline-includes":false,"preserve-yaml":false,"latex-auto-mk":true,"latex-auto-install":true,"latex-clean":true,"latex-min-runs":1,"latex-max-runs":10,"latex-makeindex":"makeindex","latex-makeindex-opts":[],"latex-tlmgr-opts":[],"latex-input-paths":[],"latex-output-dir":null,"link-external-icon":false,"link-external-newwindow":false,"self-contained-math":false,"format-resources":[],"notebook-links":true,"brand":{"light":{"brand":{"defaults":{"bootstrap":{"defaults":{"navbar-bg":"#2C3E50","navbar-fg":"#FFFFFF","navbar-hl":"#1ABC9C"}}}},"data":{"defaults":{"bootstrap":{"defaults":{"navbar-bg":"#2C3E50","navbar-fg":"#FFFFFF","navbar-hl":"#1ABC9C"}}}},"brandDir":"/Users/rejeler/Documents/Tamil/Rejeleene","projectDir":"/Users/rejeler/Documents/Tamil/Rejeleene","processedData":{"color":{},"typography":{},"logo":{"images":{}}}}}},"pandoc":{"standalone":true,"wrap":"none","default-image-extension":"png","to":"html","css":["../../styles.css"],"toc":true,"toc-depth":3,"number-sections":true,"output-file":"index.html"},"language":{"toc-title-document":"Table of contents","toc-title-website":"On this page","related-formats-title":"Other Formats","related-notebooks-title":"Notebooks","source-notebooks-prefix":"Source","other-links-title":"Other Links","code-links-title":"Code Links","launch-dev-container-title":"Launch Dev Container","launch-binder-title":"Launch Binder","article-notebook-label":"Article Notebook","notebook-preview-download":"Download Notebook","notebook-preview-download-src":"Download Source","notebook-preview-back":"Back to Article","manuscript-meca-bundle":"MECA Bundle","section-title-abstract":"Abstract","section-title-appendices":"Appendices","section-title-footnotes":"Footnotes","section-title-references":"References","section-title-reuse":"Reuse","section-title-copyright":"Copyright","section-title-citation":"Citation","appendix-attribution-cite-as":"For attribution, please cite this work as:","appendix-attribution-bibtex":"BibTeX citation:","appendix-view-license":"View License","title-block-author-single":"Author","title-block-author-plural":"Authors","title-block-affiliation-single":"Affiliation","title-block-affiliation-plural":"Affiliations","title-block-published":"Published","title-block-modified":"Modified","title-block-keywords":"Keywords","callout-tip-title":"Tip","callout-note-title":"Note","callout-warning-title":"Warning","callout-important-title":"Important","callout-caution-title":"Caution","code-summary":"Code","code-tools-menu-caption":"Code","code-tools-show-all-code":"Show All Code","code-tools-hide-all-code":"Hide All Code","code-tools-view-source":"View Source","code-tools-source-code":"Source Code","tools-share":"Share","tools-download":"Download","code-line":"Line","code-lines":"Lines","copy-button-tooltip":"Copy to Clipboard","copy-button-tooltip-success":"Copied!","repo-action-links-edit":"Edit this page","repo-action-links-source":"View source","repo-action-links-issue":"Report an issue","back-to-top":"Back to top","search-no-results-text":"No results","search-matching-documents-text":"matching documents","search-copy-link-title":"Copy link to search","search-hide-matches-text":"Hide additional matches","search-more-match-text":"more match in this document","search-more-matches-text":"more matches in this document","search-clear-button-title":"Clear","search-text-placeholder":"","search-detached-cancel-button-title":"Cancel","search-submit-button-title":"Submit","search-label":"Search","toggle-section":"Toggle section","toggle-sidebar":"Toggle sidebar navigation","toggle-dark-mode":"Toggle dark mode","toggle-reader-mode":"Toggle reader mode","toggle-navigation":"Toggle navigation","crossref-fig-title":"Figure","crossref-tbl-title":"Table","crossref-lst-title":"Listing","crossref-thm-title":"Theorem","crossref-lem-title":"Lemma","crossref-cor-title":"Corollary","crossref-prp-title":"Proposition","crossref-cnj-title":"Conjecture","crossref-def-title":"Definition","crossref-exm-title":"Example","crossref-exr-title":"Exercise","crossref-ch-prefix":"Chapter","crossref-apx-prefix":"Appendix","crossref-sec-prefix":"Section","crossref-eq-prefix":"Equation","crossref-lof-title":"List of Figures","crossref-lot-title":"List of Tables","crossref-lol-title":"List of Listings","environment-proof-title":"Proof","environment-remark-title":"Remark","environment-solution-title":"Solution","listing-page-order-by":"Order By","listing-page-order-by-default":"Default","listing-page-order-by-date-asc":"Oldest","listing-page-order-by-date-desc":"Newest","listing-page-order-by-number-desc":"High to Low","listing-page-order-by-number-asc":"Low to High","listing-page-field-date":"Date","listing-page-field-title":"Title","listing-page-field-description":"Description","listing-page-field-author":"Author","listing-page-field-filename":"File Name","listing-page-field-filemodified":"Modified","listing-page-field-subtitle":"Subtitle","listing-page-field-readingtime":"Reading Time","listing-page-field-wordcount":"Word Count","listing-page-field-categories":"Categories","listing-page-minutes-compact":"{0} min","listing-page-category-all":"All","listing-page-no-matches":"No matching items","listing-page-words":"{0} words","listing-page-filter":"Filter","draft":"Draft"},"metadata":{"lang":"en","fig-responsive":true,"quarto-version":"1.7.32","margin-header":"../../subscribe.html","theme":"cosmo","title-block-banner":false,"author":"Rick Rejeleene","date-format":"MMMM D, YYYY","page-layout":"article","title":"Why Overpopulation Isn’t India’s Main Problem","subtitle":"How majority of land is underutilized and large scale employment is missing","date":"2025-10-25","categories":["India","Economy","Tamil Nadu","Geography","Land"],"description":"The Real Challenge is in Land Use and generating large scale employment","toc-title":"Table of Contents","toc-location":"left","number-depth":2},"extensions":{"book":{"multiFile":true}}}},"projectFormats":["html"]}